virtualenv_rewrite-14.7.0.dist-info/DESCRIPTION.rst
virtualenv_rewrite-14.7.0.dist-info/METADATA
virtualenv_rewrite-14.7.0.dist-info/entry_points.txt
virtualenv_rewrite-14.7.0.dist-info/top_level.txt
virtualenv_rewrite-14.7.0.dist-info/RECORD
virtualenv_rewrite-14.7.0.dist-info/WHEEL
virtualenv_rewrite-14.7.0.dist-info/metadata.json
virtualenv/cli.py
virtualenv/__main__.py
virtualenv/core.py
virtualenv/__init__.py
virtualenv/_utils.py
virtualenv/__about__.py
virtualenv/_compat.py
virtualenv/flavors/base.py
virtualenv/flavors/posix.py
virtualenv/flavors/windows.py
virtualenv/flavors/__init__.py
virtualenv/_scripts/activate.csh
virtualenv/_scripts/activate.ps1
virtualenv/_scripts/activate.fish
virtualenv/_scripts/activate.sh
virtualenv/_scripts/deactivate.bat
virtualenv/_scripts/activate.bat
virtualenv/_scripts/activate_this.py
virtualenv/builders/base.py
virtualenv/builders/legacy.py
virtualenv/builders/venv.py
virtualenv/builders/__init__.py
virtualenv/_wheels/wheel-0.26.0-py2.py3-none-any.whl
virtualenv/_wheels/setuptools-19.4.1-py2.py3-none-any.whl
virtualenv/_wheels/pip-8.0.2-py2.py3-none-any.whl
virtualenv/_wheels/argparse-1.3.0-py2.py3-none-any.whl
