Metadata-Version: 2.0
Name: virtualenv-rewrite
Version: 14.7.0
Summary: Virtual Python Environment Builder (complete rewrite)
Home-page: https://github.com/ionelmc/virtualenv/
Author: Ionel Cristian Mărieș
Author-email: contact@ionelmc.ro
License: MIT
Platform: UNKNOWN
Classifier: Intended Audience :: Developers
Classifier: License :: OSI Approved :: MIT License
Classifier: Programming Language :: Python
Classifier: Programming Language :: Python :: 2
Classifier: Programming Language :: Python :: 2.6
Classifier: Programming Language :: Python :: 2.7
Classifier: Programming Language :: Python :: 3
Classifier: Programming Language :: Python :: 3.2
Classifier: Programming Language :: Python :: 3.3
Classifier: Programming Language :: Python :: 3.4
Requires-Dist: click (<6.0)
